dataframe_expressions/DataFrame.py
dataframe_expressions/__init__.py
dataframe_expressions/alias.py
dataframe_expressions/asts.py
dataframe_expressions/render.py
dataframe_expressions/utils.py
dataframe_expressions/utils_ast.py
dataframe_expressions-1.0.0.dist-info/LICENSE
dataframe_expressions-1.0.0.dist-info/METADATA
dataframe_expressions-1.0.0.dist-info/WHEEL
dataframe_expressions-1.0.0.dist-info/top_level.txt
dataframe_expressions-1.0.0.dist-info/RECORD
