Metadata-Version: 2.1
Name: dataframe-expressions
Version: 1.0.0
Summary: Library to help with accumulating expressions
Home-page: https://github.com/gordonwatts/dataframe_expressions
Author: G. Watts (IRIS-HEP/UW Seattle)
Author-email: gwatts@uw.edu
Maintainer: Gordon Watts (IRIS-HEP/UW Seattle)
Maintainer-email: gwatts@uw.edu
License: TBD
Platform: Any
Classifier: Intended Audience :: Developers
Classifier: Intended Audience :: Information Technology
Classifier: Programming Language :: Python
Classifier: Programming Language :: Python :: 3.7
Classifier: Topic :: Software Development
Classifier: Topic :: Utilities
Requires-Python: >=3.6, <3.8
Provides-Extra: complete
Requires-Dist: coverage ; extra == 'complete'
Requires-Dist: flake8 ; extra == 'complete'
Requires-Dist: numpy ; extra == 'complete'
Requires-Dist: pytest ; extra == 'complete'
Requires-Dist: pytest-asyncio ; extra == 'complete'
Requires-Dist: pytest-cov ; extra == 'complete'
Requires-Dist: twine ; extra == 'complete'
Requires-Dist: wheel ; extra == 'complete'
Provides-Extra: test
Requires-Dist: pytest ; extra == 'test'
Requires-Dist: pytest-asyncio ; extra == 'test'
Requires-Dist: pytest-cov ; extra == 'test'
Requires-Dist: flake8 ; extra == 'test'
Requires-Dist: coverage ; extra == 'test'
Requires-Dist: twine ; extra == 'test'
Requires-Dist: wheel ; extra == 'test'
Requires-Dist: numpy ; extra == 'test'
